[
	{"Word": "北海道",	"Reading": "ほっかいどう"},
	{"Word": "青森県",	"Reading": "あおもりけん"},
	{"Word": "秋田県",	"Reading": "あきたけん"},
	{"Word": "岩手県",	"Reading": "いわてけん"},
	{"Word": "山形県",	"Reading": "やまがたけん"},
	{"Word": "宮城県",	"Reading": "みやぎけん"},
	{"Word": "福島県",	"Reading": "ふくしまけん"},
	{"Word": "新潟県",	"Reading": "にいがたけん"},
	{"Word": "富山県",	"Reading": "とやまけん"},
	{"Word": "石川県",	"Reading": "いしかわけん"},
	{"Word": "福井県",	"Reading": "ふくいけん"},
	{"Word": "長野県",	"Reading": "ながのけん"},
	{"Word": "群馬県",	"Reading": "ぐんまけん"},
	{"Word": "栃木県",	"Reading": "とちぎけん"},
	{"Word": "茨城県",	"Reading": "いばらきけん"},
	{"Word": "千葉県",	"Reading": "ちばけん"},
	{"Word": "埼玉県",	"Reading": "さいたまけん"},
	{"Word": "東京都",	"Reading": "とうきょうと"},
	{"Word": "神奈川県",	"Reading": "かながわけん"},
	{"Word": "山梨県",	"Reading": "やまなしけん"},
	{"Word": "静岡県",	"Reading": "しずおかけん"},
	{"Word": "愛知県",	"Reading": "あいちけん"},
	{"Word": "岐阜県",	"Reading": "ぎふけん"},
	{"Word": "三重県",	"Reading": "みえけん"},
	{"Word": "滋賀県",	"Reading": "しがけん"},
	{"Word": "京都府",	"Reading": "きょうとふ"},
	{"Word": "大阪府",	"Reading": "おおさかふ"},
	{"Word": "奈良県",	"Reading": "ならけん"},
	{"Word": "和歌山県",	"Reading": "わかやまけん"},
	{"Word": "兵庫県",	"Reading": "ひょうごけん"},
	{"Word": "鳥取県",	"Reading": "とっとりけん"},
	{"Word": "島根県",	"Reading": "しまねけん"},
	{"Word": "岡山県",	"Reading": "おかやまけん"},
	{"Word": "広島県",	"Reading": "ひろしまけん"},
	{"Word": "山口県",	"Reading": "やまぐちけん"},
	{"Word": "香川県",	"Reading": "かがわけん"},
	{"Word": "徳島県",	"Reading": "とくしまけん"},
	{"Word": "高知県",	"Reading": "こうちけん"},
	{"Word": "愛媛県",	"Reading": "えひめけん"},
	{"Word": "福岡県",	"Reading": "ふくおかけん"},
	{"Word": "大分県",	"Reading": "おおいたけん"},
	{"Word": "宮崎県",	"Reading": "みやざきけん"},
	{"Word": "熊本県",	"Reading": "くまもとけん"},
	{"Word": "鹿児島県",	"Reading": "かごしまけん"},
	{"Word": "佐賀県",	"Reading": "さがけん"},
	{"Word": "長崎県",	"Reading": "ながさきけん"},
	{"Word": "沖縄県",	"Reading": "おきなわけん"}
]
